mermaidgui_py/__init__.py
mermaidgui_py/class_diagram.py
mermaidgui_py/core.py
mermaidgui_py/flowchart.py
mermaidgui_py/sequence.py
mermaidgui_py-0.0.1.dist-info/licenses/LICENSE
mermaidgui_py-0.0.1.dist-info/METADATA
mermaidgui_py-0.0.1.dist-info/WHEEL
mermaidgui_py-0.0.1.dist-info/top_level.txt
mermaidgui_py-0.0.1.dist-info/RECORD
