Metadata-Version: 2.4
Name: mermaidgui_py
Version: 0.0.1
Summary: A Python library to easily create and manage Mermaid diagrams programmatically, with strong GUI integration support.
Author-email: GeunWoo Seok <bearman.entp@gmail.com>
License: MIT
Project-URL: Homepage, https://github.com/bearmanentp/mermaidgui_py
Project-URL: BugTracker, https://github.com/bearmanentp/mermaidgui_py/issues
Keywords: mermaid,diagram,chart,flowchart,sequence diagram,class diagram,visualization,gui,pyside6
Classifier: Programming Language :: Python :: 3
Classifier: License :: OSI Approved :: MIT License
Classifier: Operating System :: OS Independent
Classifier: Topic :: Software Development :: Documentation
Classifier: Topic :: Scientific/Engineering :: Visualization
Classifier: Development Status :: 3 - Alpha
Classifier: Intended Audience :: Developers
Classifier: Intended Audience :: End Users/Desktop
Requires-Python: >=3.9
License-File: LICENSE
Requires-Dist: PySide6
Requires-Dist: PySide6-WebEngineWidgets
Dynamic: license-file
